agcod/__init__.py
agcod/client.py
agcod-0.0.1.dist-info/METADATA
agcod-0.0.1.dist-info/RECORD
agcod-0.0.1.dist-info/WHEEL
agcod-0.0.1.dist-info/top_level.txt
