Metadata-Version: 2.1
Name: agcod
Version: 0.0.1
Summary: A tool for Amazon Gift Code On-Demand (AGCOD)
Home-page: https://github.com/geekforbrains/agcod
Author: Gavin Vickery
Author-email: gavin@geekforbrains.com
License: UNKNOWN
Platform: UNKNOWN
Classifier: Programming Language :: Python :: 3
Classifier: License :: OSI Approved :: MIT License
Classifier: Operating System :: OS Independent
